{
    "data": [
        {
            "annotations": [
                {
                    "identifier": "2.16.840.1.113883.6.96",
                    "text": {
                        "de": "SNOMED Clinical Terms",
                        "en": "SNOMED Clinical Terms",
                        "fr": "SNOMED Clinical Terms",
                        "it": "SNOMED Clinical Terms",
                        "rm": "SNOMED Clinical Terms"
                    },
                    "title": "SNOMED Clinical Terms",
                    "type": "CodeSystem"
                },
                {
                    "identifier": "end",
                    "text": {
                        "en": "01.06.2100"
                    },
                    "title": "end",
                    "type": "Period"
                },
                {
                    "identifier": "start",
                    "text": {
                        "en": "01.06.2024"
                    },
                    "title": "start",
                    "type": "Period"
                },
                {
                    "identifier": "900000000000549004",
                    "text": {
                        "de": "Anamnese",
                        "en": "History and physical report",
                        "fr": "anamnèse",
                        "it": "anamnesi",
                        "rm": "anamnesa"
                    },
                    "title": "Designation",
                    "type": "Designation"
                }
            ],
            "code": "371529009",
            "name": {
                "de": "Anamnese",
                "en": "History and physical report (record artifact)",
                "fr": "anamnèse",
                "it": "anamnesi",
                "rm": "anamnesa"
            }
        },
        {
            "annotations": [
                {
                    "identifier": "2.16.840.1.113883.6.96",
                    "text": {
                        "de": "SNOMED Clinical Terms",
                        "en": "SNOMED Clinical Terms",
                        "fr": "SNOMED Clinical Terms",
                        "it": "SNOMED Clinical Terms",
                        "rm": "SNOMED Clinical Terms"
                    },
                    "title": "SNOMED Clinical Terms",
                    "type": "CodeSystem"
                },
                {
                    "identifier": "end",
                    "text": {
                        "en": "01.06.2100"
                    },
                    "title": "end",
                    "type": "Period"
                },
                {
                    "identifier": "start",
                    "text": {
                        "en": "01.06.2024"
                    },
                    "title": "start",
                    "type": "Period"
                },
                {
                    "identifier": "900000000000549004",
                    "text": {
                        "de": "Sonstige Dokumentation",
                        "en": "Record artifact",
                        "fr": "autre documentation",
                        "it": "altra documentazione",
                        "rm": "autra documentaziun"
                    },
                    "title": "Designation",
                    "type": "Designation"
                }
            ],
            "code": "419891008",
            "name": {
                "de": "Sonstige Dokumentation",
                "en": "Record artifact (record artifact)",
                "fr": "autre documentation",
                "it": "altra documentazione",
                "rm": "autra documentaziun"
            }
        },
        {
            "annotations": [
                {
                    "identifier": "2.16.840.1.113883.6.96",
                    "text": {
                        "de": "SNOMED Clinical Terms",
                        "en": "SNOMED Clinical Terms",
                        "fr": "SNOMED Clinical Terms",
                        "it": "SNOMED Clinical Terms",
                        "rm": "SNOMED Clinical Terms"
                    },
                    "title": "SNOMED Clinical Terms",
                    "type": "CodeSystem"
                },
                {
                    "identifier": "end",
                    "text": {
                        "en": "01.06.2100"
                    },
                    "title": "end",
                    "type": "Period"
                },
                {
                    "identifier": "start",
                    "text": {
                        "en": "01.06.2024"
                    },
                    "title": "start",
                    "type": "Period"
                },
                {
                    "identifier": "900000000000549004",
                    "text": {
                        "de": "Laborauftrag",
                        "en": "Laboratory Order",
                        "fr": "demande de laboratoire",
                        "it": "richiesta di laboratorio",
                        "rm": "incumbensa da labor"
                    },
                    "title": "Designation",
                    "type": "Designation"
                }
            ],
            "code": "721965002",
            "name": {
                "de": "Laborauftrag",
                "en": "Laboratory order (record artifact)",
                "fr": "demande de laboratoire",
                "it": "richiesta di laboratorio",
                "rm": "incumbensa da labor"
            }
        },
        {
            "annotations": [
                {
                    "identifier": "2.16.840.1.113883.6.96",
                    "text": {
                        "de": "SNOMED Clinical Terms",
                        "en": "SNOMED Clinical Terms",
                        "fr": "SNOMED Clinical Terms",
                        "it": "SNOMED Clinical Terms",
                        "rm": "SNOMED Clinical Terms"
                    },
                    "title": "SNOMED Clinical Terms",
                    "type": "CodeSystem"
                },
                {
                    "identifier": "end",
                    "text": {
                        "en": "01.06.2100"
                    },
                    "title": "end",
                    "type": "Period"
                },
                {
                    "identifier": "start",
                    "text": {
                        "en": "01.06.2024"
                    },
                    "title": "start",
                    "type": "Period"
                },
                {
                    "identifier": "900000000000549004",
                    "text": {
                        "de": "Pathologieauftrag",
                        "en": "Pathology order",
                        "fr": "demande de pathologie",
                        "it": "richiesta di patologia",
                        "rm": "incumbensa da patologia"
                    },
                    "title": "Designation",
                    "type": "Designation"
                }
            ],
            "code": "721966001",
            "name": {
                "de": "Pathologieauftrag",
                "en": "Pathology order (record artifact)",
                "fr": "demande de pathologie",
                "it": "richiesta di patologia",
                "rm": "incumbensa da patologia"
            }
        },
        {
            "annotations": [
                {
                    "identifier": "2.16.756.5.30.1.127.3.4",
                    "text": {
                        "de": "SNOMED Clinical Terms Swiss Extension",
                        "en": "SNOMED Clinical Terms Swiss Extension",
                        "fr": "SNOMED Clinical Terms Swiss Extension",
                        "it": "SNOMED Clinical Terms Swiss Extension",
                        "rm": "SNOMED Clinical Terms Swiss Extension"
                    },
                    "title": "SNOMED Clinical Terms Swiss Extension",
                    "type": "CodeSystem"
                },
                {
                    "identifier": "end",
                    "text": {
                        "en": "01.06.2100"
                    },
                    "title": "end",
                    "type": "Period"
                },
                {
                    "identifier": "start",
                    "text": {
                        "en": "01.06.2024"
                    },
                    "title": "start",
                    "type": "Period"
                },
                {
                    "identifier": "900000000000549004",
                    "text": {
                        "de": "Bildgebungsauftrag",
                        "en": "Imaging Order",
                        "fr": "demande d'imagerie",
                        "it": "richiesta di immaginografia",
                        "rm": "incumbensa da far in maletg"
                    },
                    "title": "Designation",
                    "type": "Designation"
                }
            ],
            "code": "2161000195103",
            "name": {
                "de": "Bildgebungsauftrag",
                "en": "Imaging order (record artifact)",
                "fr": "demande d'imagerie",
                "it": "richiesta di immaginografia",
                "rm": "incumbensa da far in maletg"
            }
        },
        {
            "annotations": [
                {
                    "identifier": "2.16.840.1.113883.6.96",
                    "text": {
                        "de": "SNOMED Clinical Terms",
                        "en": "SNOMED Clinical Terms",
                        "fr": "SNOMED Clinical Terms",
                        "it": "SNOMED Clinical Terms",
                        "rm": "SNOMED Clinical Terms"
                    },
                    "title": "SNOMED Clinical Terms",
                    "type": "CodeSystem"
                },
                {
                    "identifier": "end",
                    "text": {
                        "en": "01.06.2100"
                    },
                    "title": "end",
                    "type": "Period"
                },
                {
                    "identifier": "start",
                    "text": {
                        "en": "01.06.2024"
                    },
                    "title": "start",
                    "type": "Period"
                },
                {
                    "identifier": "900000000000549004",
                    "text": {
                        "de": "Bericht zur Bildgebung",
                        "en": "Imaging report",
                        "fr": "rapport sur l'imagerie",
                        "it": "referto di immaginografia",
                        "rm": "rapport dals maletgs"
                    },
                    "title": "Designation",
                    "type": "Designation"
                }
            ],
            "code": "4201000179104",
            "name": {
                "de": "Bericht zur Bildgebung",
                "en": "Imaging report (record artifact)",
                "fr": "rapport sur l'imagerie",
                "it": "referto di immaginografia",
                "rm": "rapport dals maletgs"
            }
        },
        {
            "annotations": [
                {
                    "identifier": "2.16.840.1.113883.6.96",
                    "text": {
                        "de": "SNOMED Clinical Terms",
                        "en": "SNOMED Clinical Terms",
                        "fr": "SNOMED Clinical Terms",
                        "it": "SNOMED Clinical Terms",
                        "rm": "SNOMED Clinical Terms"
                    },
                    "title": "SNOMED Clinical Terms",
                    "type": "CodeSystem"
                },
                {
                    "identifier": "end",
                    "text": {
                        "en": "01.06.2100"
                    },
                    "title": "end",
                    "type": "Period"
                },
                {
                    "identifier": "start",
                    "text": {
                        "en": "01.06.2024"
                    },
                    "title": "start",
                    "type": "Period"
                },
                {
                    "identifier": "900000000000549004",
                    "text": {
                        "de": "Ärztlicher behandlungsplan",
                        "en": "Medical care plan",
                        "fr": "plan de traitement médical",
                        "it": "piano di cure mediche",
                        "rm": "plan da tractament medical"
                    },
                    "title": "Designation",
                    "type": "Designation"
                }
            ],
            "code": "737427001",
            "name": {
                "de": "Ärztlicher behandlungsplan",
                "en": "Clinical management plan (record artifact)",
                "fr": "plan de traitement médical",
                "it": "piano di cure mediche",
                "rm": "plan da tractament medical"
            }
        },
        {
            "annotations": [
                {
                    "identifier": "2.16.840.1.113883.6.96",
                    "text": {
                        "de": "SNOMED Clinical Terms",
                        "en": "SNOMED Clinical Terms",
                        "fr": "SNOMED Clinical Terms",
                        "it": "SNOMED Clinical Terms",
                        "rm": "SNOMED Clinical Terms"
                    },
                    "title": "SNOMED Clinical Terms",
                    "type": "CodeSystem"
                },
                {
                    "identifier": "end",
                    "text": {
                        "en": "01.06.2100"
                    },
                    "title": "end",
                    "type": "Period"
                },
                {
                    "identifier": "start",
                    "text": {
                        "en": "01.06.2024"
                    },
                    "title": "start",
                    "type": "Period"
                },
                {
                    "identifier": "900000000000549004",
                    "text": {
                        "de": "Nicht-Arzneimittel-Verschreibung",
                        "en": "Non-drug prescription",
                        "fr": "prescription non médicamenteuse",
                        "it": "prescrizione non di medicamenti",
                        "rm": "prescripziun senza medischinas"
                    },
                    "title": "Designation",
                    "type": "Designation"
                }
            ],
            "code": "765492005",
            "name": {
                "de": "Nicht-Arzneimittel-Verschreibung",
                "en": "Non-drug prescription record (record artifact)",
                "fr": "prescription non médicamenteuse",
                "it": "prescrizione non di medicamenti",
                "rm": "prescripziun senza medischinas"
            }
        },
        {
            "annotations": [
                {
                    "identifier": "2.16.840.1.113883.6.96",
                    "text": {
                        "de": "SNOMED Clinical Terms",
                        "en": "SNOMED Clinical Terms",
                        "fr": "SNOMED Clinical Terms",
                        "it": "SNOMED Clinical Terms",
                        "rm": "SNOMED Clinical Terms"
                    },
                    "title": "SNOMED Clinical Terms",
                    "type": "CodeSystem"
                },
                {
                    "identifier": "end",
                    "text": {
                        "en": "01.06.2100"
                    },
                    "title": "end",
                    "type": "Period"
                },
                {
                    "identifier": "start",
                    "text": {
                        "en": "01.06.2024"
                    },
                    "title": "start",
                    "type": "Period"
                },
                {
                    "identifier": "900000000000549004",
                    "text": {
                        "de": "Pflegeplan",
                        "en": "Nursing care plan",
                        "fr": "plan de soins infirmier",
                        "it": "piano di cure infermieristiche",
                        "rm": "plan da tgira"
                    },
                    "title": "Designation",
                    "type": "Designation"
                }
            ],
            "code": "773130005",
            "name": {
                "de": "Pflegeplan",
                "en": "Nursing care plan (record artifact)",
                "fr": "plan de soins infirmier",
                "it": "piano di cure infermieristiche",
                "rm": "plan da tgira"
            }
        },
        {
            "annotations": [
                {
                    "identifier": "2.16.840.1.113883.6.96",
                    "text": {
                        "de": "SNOMED Clinical Terms",
                        "en": "SNOMED Clinical Terms",
                        "fr": "SNOMED Clinical Terms",
                        "it": "SNOMED Clinical Terms",
                        "rm": "SNOMED Clinical Terms"
                    },
                    "title": "SNOMED Clinical Terms",
                    "type": "CodeSystem"
                },
                {
                    "identifier": "end",
                    "text": {
                        "en": "01.06.2100"
                    },
                    "title": "end",
                    "type": "Period"
                },
                {
                    "identifier": "start",
                    "text": {
                        "en": "01.06.2024"
                    },
                    "title": "start",
                    "type": "Period"
                },
                {
                    "identifier": "900000000000549004",
                    "text": {
                        "de": "Rehabilitationsplan",
                        "en": "Rehabilitation care plan",
                        "fr": "plan de réhabilitation",
                        "it": "piano di riabilitazione",
                        "rm": "plan da reabilitaziun"
                    },
                    "title": "Designation",
                    "type": "Designation"
                }
            ],
            "code": "736055001",
            "name": {
                "de": "Rehabilitationsplan",
                "en": "Rehabilitation care plan (record artifact)",
                "fr": "plan de réhabilitation",
                "it": "piano di riabilitazione",
                "rm": "plan da reabilitaziun"
            }
        },
        {
            "annotations": [
                {
                    "identifier": "2.16.840.1.113883.6.96",
                    "text": {
                        "de": "SNOMED Clinical Terms",
                        "en": "SNOMED Clinical Terms",
                        "fr": "SNOMED Clinical Terms",
                        "it": "SNOMED Clinical Terms",
                        "rm": "SNOMED Clinical Terms"
                    },
                    "title": "SNOMED Clinical Terms",
                    "type": "CodeSystem"
                },
                {
                    "identifier": "end",
                    "text": {
                        "en": "01.06.2100"
                    },
                    "title": "end",
                    "type": "Period"
                },
                {
                    "identifier": "start",
                    "text": {
                        "en": "01.06.2024"
                    },
                    "title": "start",
                    "type": "Period"
                },
                {
                    "identifier": "900000000000549004",
                    "text": {
                        "de": "Arzneimittelrezept",
                        "en": "Medical Prescription record",
                        "fr": "prescription de médicaments",
                        "it": "prescrizione di medicamenti",
                        "rm": "recept da medicaments"
                    },
                    "title": "Designation",
                    "type": "Designation"
                }
            ],
            "code": "761938008",
            "name": {
                "de": "Arzneimittelrezept",
                "en": "Medicinal prescription record (record artifact)",
                "fr": "prescription de médicaments",
                "it": "prescrizione di medicamenti",
                "rm": "recept da medicaments"
            }
        },
        {
            "annotations": [
                {
                    "identifier": "2.16.840.1.113883.6.96",
                    "text": {
                        "de": "SNOMED Clinical Terms",
                        "en": "SNOMED Clinical Terms",
                        "fr": "SNOMED Clinical Terms",
                        "it": "SNOMED Clinical Terms",
                        "rm": "SNOMED Clinical Terms"
                    },
                    "title": "SNOMED Clinical Terms",
                    "type": "CodeSystem"
                },
                {
                    "identifier": "end",
                    "text": {
                        "en": "01.06.2100"
                    },
                    "title": "end",
                    "type": "Period"
                },
                {
                    "identifier": "start",
                    "text": {
                        "en": "01.06.2024"
                    },
                    "title": "start",
                    "type": "Period"
                },
                {
                    "identifier": "900000000000549004",
                    "text": {
                        "de": "Allergieausweis",
                        "en": "Allergy record",
                        "fr": "carnet des allergies",
                        "it": "passaporto delle allergie",
                        "rm": "attest d'allergia"
                    },
                    "title": "Designation",
                    "type": "Designation"
                }
            ],
            "code": "722446000",
            "name": {
                "de": "Allergieausweis",
                "en": "Allergy record (record artifact)",
                "fr": "carnet des allergies",
                "it": "passaporto delle allergie",
                "rm": "attest d'allergia"
            }
        },
        {
            "annotations": [
                {
                    "identifier": "2.16.840.1.113883.6.96",
                    "text": {
                        "de": "SNOMED Clinical Terms",
                        "en": "SNOMED Clinical Terms",
                        "fr": "SNOMED Clinical Terms",
                        "it": "SNOMED Clinical Terms",
                        "rm": "SNOMED Clinical Terms"
                    },
                    "title": "SNOMED Clinical Terms",
                    "type": "CodeSystem"
                },
                {
                    "identifier": "end",
                    "text": {
                        "en": "01.06.2100"
                    },
                    "title": "end",
                    "type": "Period"
                },
                {
                    "identifier": "start",
                    "text": {
                        "en": "01.06.2024"
                    },
                    "title": "start",
                    "type": "Period"
                },
                {
                    "identifier": "900000000000549004",
                    "text": {
                        "de": "Ärztliches Attest",
                        "en": "Medical certificate",
                        "fr": "certificat médical",
                        "it": "certificato medico",
                        "rm": "attest medical"
                    },
                    "title": "Designation",
                    "type": "Designation"
                }
            ],
            "code": "772786005",
            "name": {
                "de": "Ärztliches Attest",
                "en": "Medical certificate (record artifact)",
                "fr": "certificat médical",
                "it": "certificato medico",
                "rm": "attest medical"
            }
        },
        {
            "annotations": [
                {
                    "identifier": "2.16.840.1.113883.6.96",
                    "text": {
                        "de": "SNOMED Clinical Terms",
                        "en": "SNOMED Clinical Terms",
                        "fr": "SNOMED Clinical Terms",
                        "it": "SNOMED Clinical Terms",
                        "rm": "SNOMED Clinical Terms"
                    },
                    "title": "SNOMED Clinical Terms",
                    "type": "CodeSystem"
                },
                {
                    "identifier": "end",
                    "text": {
                        "en": "01.06.2100"
                    },
                    "title": "end",
                    "type": "Period"
                },
                {
                    "identifier": "start",
                    "text": {
                        "en": "01.06.2024"
                    },
                    "title": "start",
                    "type": "Period"
                },
                {
                    "identifier": "900000000000549004",
                    "text": {
                        "de": "Austrittsbericht",
                        "en": "Discharge summary",
                        "fr": "rapport de sortie",
                        "it": "rapporto di dimissione",
                        "rm": "rapport d'extrada"
                    },
                    "title": "Designation",
                    "type": "Designation"
                }
            ],
            "code": "373942005",
            "name": {
                "de": "Austrittsbericht",
                "en": "Discharge summary (record artifact)",
                "fr": "rapport de sortie",
                "it": "rapporto di dimissione",
                "rm": "rapport d'extrada"
            }
        },
        {
            "annotations": [
                {
                    "identifier": "2.16.840.1.113883.6.96",
                    "text": {
                        "de": "SNOMED Clinical Terms",
                        "en": "SNOMED Clinical Terms",
                        "fr": "SNOMED Clinical Terms",
                        "it": "SNOMED Clinical Terms",
                        "rm": "SNOMED Clinical Terms"
                    },
                    "title": "SNOMED Clinical Terms",
                    "type": "CodeSystem"
                },
                {
                    "identifier": "end",
                    "text": {
                        "en": "01.06.2100"
                    },
                    "title": "end",
                    "type": "Period"
                },
                {
                    "identifier": "start",
                    "text": {
                        "en": "01.06.2024"
                    },
                    "title": "start",
                    "type": "Period"
                },
                {
                    "identifier": "900000000000549004",
                    "text": {
                        "de": "Überweisungsbericht",
                        "en": "Transfer summary report",
                        "fr": "rapport de transfert",
                        "it": "rapporto di trasferimento",
                        "rm": "rapport d'assegnaziun"
                    },
                    "title": "Designation",
                    "type": "Designation"
                }
            ],
            "code": "371535009",
            "name": {
                "de": "Überweisungsbericht",
                "en": "Transfer summary report (record artifact)",
                "fr": "rapport de transfert",
                "it": "rapporto di trasferimento",
                "rm": "rapport d'assegnaziun"
            }
        },
        {
            "annotations": [
                {
                    "identifier": "2.16.840.1.113883.6.96",
                    "text": {
                        "de": "SNOMED Clinical Terms",
                        "en": "SNOMED Clinical Terms",
                        "fr": "SNOMED Clinical Terms",
                        "it": "SNOMED Clinical Terms",
                        "rm": "SNOMED Clinical Terms"
                    },
                    "title": "SNOMED Clinical Terms",
                    "type": "CodeSystem"
                },
                {
                    "identifier": "end",
                    "text": {
                        "en": "01.06.2100"
                    },
                    "title": "end",
                    "type": "Period"
                },
                {
                    "identifier": "start",
                    "text": {
                        "en": "01.06.2024"
                    },
                    "title": "start",
                    "type": "Period"
                },
                {
                    "identifier": "900000000000549004",
                    "text": {
                        "de": "Notfallbericht",
                        "en": "Emergency report",
                        "fr": "rapport d'urgence",
                        "it": "rapporto d'urgenza",
                        "rm": "rapport davart in cas d'urgenza"
                    },
                    "title": "Designation",
                    "type": "Designation"
                }
            ],
            "code": "445300006",
            "name": {
                "de": "Notfallbericht",
                "en": "Emergency department record (record artifact)",
                "fr": "rapport d'urgence",
                "it": "rapporto d'urgenza",
                "rm": "rapport davart in cas d'urgenza"
            }
        },
        {
            "annotations": [
                {
                    "identifier": "2.16.840.1.113883.6.96",
                    "text": {
                        "de": "SNOMED Clinical Terms",
                        "en": "SNOMED Clinical Terms",
                        "fr": "SNOMED Clinical Terms",
                        "it": "SNOMED Clinical Terms",
                        "rm": "SNOMED Clinical Terms"
                    },
                    "title": "SNOMED Clinical Terms",
                    "type": "CodeSystem"
                },
                {
                    "identifier": "end",
                    "text": {
                        "en": "01.06.2100"
                    },
                    "title": "end",
                    "type": "Period"
                },
                {
                    "identifier": "start",
                    "text": {
                        "en": "01.06.2024"
                    },
                    "title": "start",
                    "type": "Period"
                },
                {
                    "identifier": "900000000000549004",
                    "text": {
                        "de": "Nichtmedizinischer Bericht",
                        "en": "Non-medical report",
                        "fr": "rapport non médical",
                        "it": "rapporto non medico",
                        "rm": "rapport nunmedical"
                    },
                    "title": "Designation",
                    "type": "Designation"
                }
            ],
            "code": "445418005",
            "name": {
                "de": "Nichtmedizinischer Bericht",
                "en": "Professional allied to medicine clinical report (record artifact)",
                "fr": "rapport non médical",
                "it": "rapporto non medico",
                "rm": "rapport nunmedical"
            }
        },
        {
            "annotations": [
                {
                    "identifier": "2.16.840.1.113883.6.96",
                    "text": {
                        "de": "SNOMED Clinical Terms",
                        "en": "SNOMED Clinical Terms",
                        "fr": "SNOMED Clinical Terms",
                        "it": "SNOMED Clinical Terms",
                        "rm": "SNOMED Clinical Terms"
                    },
                    "title": "SNOMED Clinical Terms",
                    "type": "CodeSystem"
                },
                {
                    "identifier": "end",
                    "text": {
                        "en": "01.06.2100"
                    },
                    "title": "end",
                    "type": "Period"
                },
                {
                    "identifier": "start",
                    "text": {
                        "en": "01.06.2024"
                    },
                    "title": "start",
                    "type": "Period"
                },
                {
                    "identifier": "900000000000549004",
                    "text": {
                        "de": "Konsultationsbericht",
                        "en": "Consultation report",
                        "fr": "rapport de consultation",
                        "it": "rapporto di consultazione",
                        "rm": "rapport da la consultaziun clinica"
                    },
                    "title": "Designation",
                    "type": "Designation"
                }
            ],
            "code": "371530004",
            "name": {
                "de": "Konsultationsbericht",
                "en": "Clinical consultation report (record artifact)",
                "fr": "rapport de consultation",
                "it": "rapporto di consultazione",
                "rm": "rapport da la consultaziun clinica"
            }
        },
        {
            "annotations": [
                {
                    "identifier": "2.16.840.1.113883.6.96",
                    "text": {
                        "de": "SNOMED Clinical Terms",
                        "en": "SNOMED Clinical Terms",
                        "fr": "SNOMED Clinical Terms",
                        "it": "SNOMED Clinical Terms",
                        "rm": "SNOMED Clinical Terms"
                    },
                    "title": "SNOMED Clinical Terms",
                    "type": "CodeSystem"
                },
                {
                    "identifier": "end",
                    "text": {
                        "en": "01.06.2100"
                    },
                    "title": "end",
                    "type": "Period"
                },
                {
                    "identifier": "start",
                    "text": {
                        "en": "01.06.2024"
                    },
                    "title": "start",
                    "type": "Period"
                },
                {
                    "identifier": "900000000000549004",
                    "text": {
                        "de": "Laborbericht",
                        "en": "Laboratory report",
                        "fr": "rapport de laboratoire",
                        "it": "referto di laboratorio",
                        "rm": "rapport da labor"
                    },
                    "title": "Designation",
                    "type": "Designation"
                }
            ],
            "code": "4241000179101",
            "name": {
                "de": "Laborbericht",
                "en": "Laboratory report (record artifact)",
                "fr": "rapport de laboratoire",
                "it": "referto di laboratorio",
                "rm": "rapport da labor"
            }
        },
        {
            "annotations": [
                {
                    "identifier": "2.16.840.1.113883.6.96",
                    "text": {
                        "de": "SNOMED Clinical Terms",
                        "en": "SNOMED Clinical Terms",
                        "fr": "SNOMED Clinical Terms",
                        "it": "SNOMED Clinical Terms",
                        "rm": "SNOMED Clinical Terms"
                    },
                    "title": "SNOMED Clinical Terms",
                    "type": "CodeSystem"
                },
                {
                    "identifier": "end",
                    "text": {
                        "en": "01.06.2100"
                    },
                    "title": "end",
                    "type": "Period"
                },
                {
                    "identifier": "start",
                    "text": {
                        "en": "01.06.2024"
                    },
                    "title": "start",
                    "type": "Period"
                },
                {
                    "identifier": "900000000000549004",
                    "text": {
                        "de": "Operationsbericht",
                        "en": "Operative report",
                        "fr": "rapport d'opération",
                        "it": "rapporto operatorio",
                        "rm": "rapport d'operaziun"
                    },
                    "title": "Designation",
                    "type": "Designation"
                }
            ],
            "code": "371526002",
            "name": {
                "de": "Operationsbericht",
                "en": "Operative report (record artifact)",
                "fr": "rapport d'opération",
                "it": "rapporto operatorio",
                "rm": "rapport d'operaziun"
            }
        },
        {
            "annotations": [
                {
                    "identifier": "2.16.840.1.113883.6.96",
                    "text": {
                        "de": "SNOMED Clinical Terms",
                        "en": "SNOMED Clinical Terms",
                        "fr": "SNOMED Clinical Terms",
                        "it": "SNOMED Clinical Terms",
                        "rm": "SNOMED Clinical Terms"
                    },
                    "title": "SNOMED Clinical Terms",
                    "type": "CodeSystem"
                },
                {
                    "identifier": "end",
                    "text": {
                        "en": "01.06.2100"
                    },
                    "title": "end",
                    "type": "Period"
                },
                {
                    "identifier": "start",
                    "text": {
                        "en": "01.06.2024"
                    },
                    "title": "start",
                    "type": "Period"
                },
                {
                    "identifier": "900000000000549004",
                    "text": {
                        "de": "Verlaufsbericht",
                        "en": "Progress note",
                        "fr": "rapport de suivi",
                        "it": "referto sul decorso",
                        "rm": "rapport da l'andament"
                    },
                    "title": "Designation",
                    "type": "Designation"
                }
            ],
            "code": "371532007",
            "name": {
                "de": "Verlaufsbericht",
                "en": "Progress report (record artifact)",
                "fr": "rapport de suivi",
                "it": "referto sul decorso",
                "rm": "rapport da l'andament"
            }
        },
        {
            "annotations": [
                {
                    "identifier": "2.16.840.1.113883.6.96",
                    "text": {
                        "de": "SNOMED Clinical Terms",
                        "en": "SNOMED Clinical Terms",
                        "fr": "SNOMED Clinical Terms",
                        "it": "SNOMED Clinical Terms",
                        "rm": "SNOMED Clinical Terms"
                    },
                    "title": "SNOMED Clinical Terms",
                    "type": "CodeSystem"
                },
                {
                    "identifier": "end",
                    "text": {
                        "en": "01.06.2100"
                    },
                    "title": "end",
                    "type": "Period"
                },
                {
                    "identifier": "start",
                    "text": {
                        "en": "01.06.2024"
                    },
                    "title": "start",
                    "type": "Period"
                },
                {
                    "identifier": "900000000000549004",
                    "text": {
                        "de": "Bild",
                        "en": "Image",
                        "fr": "image",
                        "it": "immagine",
                        "rm": "maletg"
                    },
                    "title": "Designation",
                    "type": "Designation"
                }
            ],
            "code": "900000000000471006",
            "name": {
                "de": "Bild",
                "en": "Image reference (foundation metadata concept)",
                "fr": "image",
                "it": "immagine",
                "rm": "maletg"
            }
        },
        {
            "annotations": [
                {
                    "identifier": "2.16.840.1.113883.6.96",
                    "text": {
                        "de": "SNOMED Clinical Terms",
                        "en": "SNOMED Clinical Terms",
                        "fr": "SNOMED Clinical Terms",
                        "it": "SNOMED Clinical Terms",
                        "rm": "SNOMED Clinical Terms"
                    },
                    "title": "SNOMED Clinical Terms",
                    "type": "CodeSystem"
                },
                {
                    "identifier": "end",
                    "text": {
                        "en": "01.06.2100"
                    },
                    "title": "end",
                    "type": "Period"
                },
                {
                    "identifier": "start",
                    "text": {
                        "en": "01.06.2024"
                    },
                    "title": "start",
                    "type": "Period"
                },
                {
                    "identifier": "900000000000549004",
                    "text": {
                        "de": "Impfdokument",
                        "en": "Immunization record",
                        "fr": "document de vaccination",
                        "it": "documento di vaccinazione",
                        "rm": "document da vaccinaziun"
                    },
                    "title": "Designation",
                    "type": "Designation"
                }
            ],
            "code": "41000179103",
            "name": {
                "de": "Impfdokument",
                "en": "Immunization record (record artifact)",
                "fr": "document de vaccination",
                "it": "documento di vaccinazione",
                "rm": "document da vaccinaziun"
            }
        },
        {
            "annotations": [
                {
                    "identifier": "2.16.840.1.113883.6.96",
                    "text": {
                        "de": "SNOMED Clinical Terms",
                        "en": "SNOMED Clinical Terms",
                        "fr": "SNOMED Clinical Terms",
                        "it": "SNOMED Clinical Terms",
                        "rm": "SNOMED Clinical Terms"
                    },
                    "title": "SNOMED Clinical Terms",
                    "type": "CodeSystem"
                },
                {
                    "identifier": "end",
                    "text": {
                        "en": "01.06.2100"
                    },
                    "title": "end",
                    "type": "Period"
                },
                {
                    "identifier": "start",
                    "text": {
                        "en": "01.06.2024"
                    },
                    "title": "start",
                    "type": "Period"
                },
                {
                    "identifier": "900000000000549004",
                    "text": {
                        "de": "Pathologiebericht",
                        "en": "Pathology report",
                        "fr": "rapport de pathologie",
                        "it": "rapporto di patologia",
                        "rm": "rapport da la patologia"
                    },
                    "title": "Designation",
                    "type": "Designation"
                }
            ],
            "code": "371528001",
            "name": {
                "de": "Pathologiebericht",
                "en": "Pathology report (record artifact)",
                "fr": "rapport de pathologie",
                "it": "rapporto di patologia",
                "rm": "rapport da la patologia"
            }
        },
        {
            "annotations": [
                {
                    "identifier": "2.16.840.1.113883.6.96",
                    "text": {
                        "de": "SNOMED Clinical Terms",
                        "en": "SNOMED Clinical Terms",
                        "fr": "SNOMED Clinical Terms",
                        "it": "SNOMED Clinical Terms",
                        "rm": "SNOMED Clinical Terms"
                    },
                    "title": "SNOMED Clinical Terms",
                    "type": "CodeSystem"
                },
                {
                    "identifier": "end",
                    "text": {
                        "en": "01.06.2100"
                    },
                    "title": "end",
                    "type": "Period"
                },
                {
                    "identifier": "start",
                    "text": {
                        "en": "01.06.2024"
                    },
                    "title": "start",
                    "type": "Period"
                },
                {
                    "identifier": "900000000000549004",
                    "text": {
                        "de": "Medikationsliste",
                        "en": "Medication list",
                        "fr": "liste des médicaments",
                        "it": "elenco dei medicamenti",
                        "rm": "glista da medicaziun"
                    },
                    "title": "Designation",
                    "type": "Designation"
                }
            ],
            "code": "721912009",
            "name": {
                "de": "Medikationsliste",
                "en": "Medication summary document (record artifact)",
                "fr": "liste des médicaments",
                "it": "elenco dei medicamenti",
                "rm": "glista da medicaziun"
            }
        },
        {
            "annotations": [
                {
                    "identifier": "2.16.840.1.113883.6.96",
                    "text": {
                        "de": "SNOMED Clinical Terms",
                        "en": "SNOMED Clinical Terms",
                        "fr": "SNOMED Clinical Terms",
                        "it": "SNOMED Clinical Terms",
                        "rm": "SNOMED Clinical Terms"
                    },
                    "title": "SNOMED Clinical Terms",
                    "type": "CodeSystem"
                },
                {
                    "identifier": "end",
                    "text": {
                        "en": "01.06.2100"
                    },
                    "title": "end",
                    "type": "Period"
                },
                {
                    "identifier": "start",
                    "text": {
                        "en": "01.06.2024"
                    },
                    "title": "start",
                    "type": "Period"
                },
                {
                    "identifier": "900000000000549004",
                    "text": {
                        "de": "Medikationsplan",
                        "en": "Medication Card document",
                        "fr": "plan de médication",
                        "it": "piano dei medicamenti",
                        "rm": "plan da mediaziun"
                    },
                    "title": "Designation",
                    "type": "Designation"
                }
            ],
            "code": "736378000",
            "name": {
                "de": "Medikationsplan",
                "en": "Medication management plan (record artifact)",
                "fr": "plan de médication",
                "it": "piano dei medicamenti",
                "rm": "plan da mediaziun"
            }
        },
        {
            "annotations": [
                {
                    "identifier": "2.16.756.5.30.1.127.3.4",
                    "text": {
                        "de": "SNOMED Clinical Terms Swiss Extension",
                        "en": "SNOMED Clinical Terms Swiss Extension",
                        "fr": "SNOMED Clinical Terms Swiss Extension",
                        "it": "SNOMED Clinical Terms Swiss Extension",
                        "rm": "SNOMED Clinical Terms Swiss Extension"
                    },
                    "title": "SNOMED Clinical Terms Swiss Extension",
                    "type": "CodeSystem"
                },
                {
                    "identifier": "end",
                    "text": {
                        "en": "01.06.2100"
                    },
                    "title": "end",
                    "type": "Period"
                },
                {
                    "identifier": "start",
                    "text": {
                        "en": "01.06.2024"
                    },
                    "title": "start",
                    "type": "Period"
                },
                {
                    "identifier": "900000000000549004",
                    "text": {
                        "de": "Medikamentenabgabe",
                        "en": "Medication dispense",
                        "fr": "dispense de médicaments",
                        "it": "dispensazione di medicamenti",
                        "rm": "dispensaziun da medicaments"
                    },
                    "title": "Designation",
                    "type": "Designation"
                }
            ],
            "code": "82291000195104",
            "name": {
                "de": "Medikamentenabgabe",
                "en": "Medication dispense document (record artifact)",
                "fr": "dispense de médicaments",
                "it": "dispensazione di medicamenti",
                "rm": "dispensaziun da medicaments"
            }
        },
        {
            "annotations": [
                {
                    "identifier": "2.16.840.1.113883.6.96",
                    "text": {
                        "de": "SNOMED Clinical Terms",
                        "en": "SNOMED Clinical Terms",
                        "fr": "SNOMED Clinical Terms",
                        "it": "SNOMED Clinical Terms",
                        "rm": "SNOMED Clinical Terms"
                    },
                    "title": "SNOMED Clinical Terms",
                    "type": "CodeSystem"
                },
                {
                    "identifier": "end",
                    "text": {
                        "en": "01.06.2100"
                    },
                    "title": "end",
                    "type": "Period"
                },
                {
                    "identifier": "start",
                    "text": {
                        "en": "01.06.2024"
                    },
                    "title": "start",
                    "type": "Period"
                },
                {
                    "identifier": "900000000000549004",
                    "text": {
                        "de": "Therapieentscheid Medikation",
                        "en": "Medication treatment plan",
                        "fr": "plan de traitement medicament",
                        "it": "decisione di terapia medicament",
                        "rm": "plan da tractament da medicaments"
                    },
                    "title": "Designation",
                    "type": "Designation"
                }
            ],
            "code": "761931002",
            "name": {
                "de": "Therapieentscheid Medikation",
                "en": "Medication treatment plan report (record artifact)",
                "fr": "plan de traitement medicament",
                "it": "decisione di terapia medicament",
                "rm": "plan da tractament da medicaments"
            }
        },
        {
            "annotations": [
                {
                    "identifier": "2.16.840.1.113883.6.96",
                    "text": {
                        "de": "SNOMED Clinical Terms",
                        "en": "SNOMED Clinical Terms",
                        "fr": "SNOMED Clinical Terms",
                        "it": "SNOMED Clinical Terms",
                        "rm": "SNOMED Clinical Terms"
                    },
                    "title": "SNOMED Clinical Terms",
                    "type": "CodeSystem"
                },
                {
                    "identifier": "end",
                    "text": {
                        "en": "01.06.2100"
                    },
                    "title": "end",
                    "type": "Period"
                },
                {
                    "identifier": "start",
                    "text": {
                        "en": "01.06.2024"
                    },
                    "title": "start",
                    "type": "Period"
                },
                {
                    "identifier": "900000000000549004",
                    "text": {
                        "de": "Bild/Video/Audio",
                        "en": "Picture/Video/Audio",
                        "fr": "image/vidéo/audio",
                        "it": "immagine/video/audio",
                        "rm": "maletg/video/audio"
                    },
                    "title": "Designation",
                    "type": "Designation"
                }
            ],
            "code": "787148009",
            "name": {
                "de": "Bild/Video/Audio",
                "en": "Digital representation of specimen (record artifact)",
                "fr": "image/vidéo/audio",
                "it": "immagine/video/audio",
                "rm": "maletg/video/audio"
            }
        }
    ]
}